MANIFEST.in
README.rst
setup.py
fontawesome_markdown/__init__.py
fontawesome_markdown/icon_list.py
fontawesome_markdown/main.py
fontawesome_markdown.egg-info/PKG-INFO
fontawesome_markdown.egg-info/SOURCES.txt
fontawesome_markdown.egg-info/dependency_links.txt
fontawesome_markdown.egg-info/not-zip-safe
fontawesome_markdown.egg-info/requires.txt
fontawesome_markdown.egg-info/top_level.txt