Metadata-Version: 1.1
Name: fontawesome-markdown
Version: 0.2.5
Summary: Font Awesome support for Markdown
Home-page: http://bmcorser.github.com/fontawesome-markdown
Author: bmcorser
Author-email: bmcorser@gmail.com
License: GPL
Platform: UNKNOWN
Classifier: Programming Language :: Python :: 2.7
Classifier: Programming Language :: Python :: 3.2
Classifier: Programming Language :: Python :: 3.4
